paragradio/__init__.py
paragradio/v2025_03/__init__.py
paragradio/v2025_03/_internal/__init__.py
paragradio/v2025_03/_internal/core.py
paragradio/v2025_03/_internal/signalsourceguisinks.py
paragradio/v2025_03/_internal/noise_tx/__init__.py
paragradio/v2025_03/_internal/noise_tx/noise_tx_gr3_10.py
paragradio/v2025_03/_internal/noise_tx/noise_tx_gr3_8.py
paragradio/v2025_03/_internal/psk_tx_loop/__init__.py
paragradio/v2025_03/_internal/psk_tx_loop/psk_tx_loop_gr3_8.py
paragradio/v2025_03/_internal/specan/__init__.py
paragradio/v2025_03/_internal/specan/specan_gr3_10.py
paragradio/v2025_03/_internal/specan/specan_gr3_8.py
paragradio/v2025_03/_internal/specansim/__init__.py
paragradio/v2025_03/_internal/specansim/simspecan_gr3_10.py
paragradio/v2025_03/_internal/specansim/simspecan_gr3_8.py
paragradio/v2025_03/_internal/wbfm_rx/__init__.py
paragradio/v2025_03/_internal/wbfm_rx/wbfm_rx_gr3_10.py
paragradio/v2025_03/_internal/wbfm_rx/wbfm_rx_gr3_8.py
paragradio/v2025_03/_internal/wbfm_tx/wbfm_tx_microphone.py
paragradio-2025.3.2.dist-info/LICENSE
paragradio-2025.3.2.dist-info/METADATA
paragradio-2025.3.2.dist-info/WHEEL
paragradio-2025.3.2.dist-info/top_level.txt
paragradio-2025.3.2.dist-info/RECORD
