Metadata-Version: 2.2
Name: paragradio
Version: 2025.3.2
Summary: Parallel GNU Radio. Launches a flowgraph using `multiprocessing`, provides methods for flowgraph. Includes pre-built flowgraphs.
Author: james-pcdr
Project-URL: Homepage, https://github.com/python-can-define-radio/side-projects/tree/main/2024_10_07_GRC_guizero_experim
Project-URL: Bug Tracker, https://github.com/python-can-define-radio/side-projects/issues
Classifier: Programming Language :: Python :: 3
Classifier: Operating System :: OS Independent
Requires-Python: <3.12,>=3.8
License-File: LICENSE
Requires-Dist: typeguard<5,>=4
